woodland/__init__.py
woodland/tree_classes.py
woodland-0.0.1.dist-info/LICENSE
woodland-0.0.1.dist-info/METADATA
woodland-0.0.1.dist-info/WHEEL
woodland-0.0.1.dist-info/top_level.txt
woodland-0.0.1.dist-info/RECORD
