Metadata-Version: 2.1
Name: woodland
Version: 0.0.1
Summary: Pre-made Tree data structure.
Home-page: https://github.com/JHowell45/Forests
Author: Jacob Howell
Author-email: email@gmail.com
License: UNKNOWN
Platform: UNKNOWN
Classifier: Development Status :: 2 - Pre-Alpha
Classifier: Programming Language :: Python
Classifier: Programming Language :: Python :: 3
Classifier: Programming Language :: Python :: 3.6
